magic8ball/__init__.py
magic8ball-1.1.2.dist-info/LICENSE
magic8ball-1.1.2.dist-info/METADATA
magic8ball-1.1.2.dist-info/WHEEL
magic8ball-1.1.2.dist-info/top_level.txt
magic8ball-1.1.2.dist-info/RECORD
