Metadata-Version: 2.1
Name: magic8ball
Version: 1.1.2
Summary: Magic 8 ball answers.
Home-page: https://github.com/realcyguy/magic8ball
Author: Cyrus Yip
Author-email: cyruscmyip1@gmail.com
License: UNKNOWN
Platform: UNKNOWN
Classifier: Programming Language :: Python :: 3
Classifier: License :: OSI Approved :: MIT License
Classifier: Operating System :: OS Independent
Requires-Python: >=3.6
